pdf_binder/__init__.py
pdf_binder/pdf_to_signatures.py
pdf_binder-0.1.dist-info/LICENSE
pdf_binder-0.1.dist-info/METADATA
pdf_binder-0.1.dist-info/WHEEL
pdf_binder-0.1.dist-info/entry_points.txt
pdf_binder-0.1.dist-info/top_level.txt
pdf_binder-0.1.dist-info/RECORD
