Metadata-Version: 2.1
Name: pdf-binder
Version: 0.1
Summary: A tool for preparing PDFs for bookbinding
Home-page: https://github.com/Peter-Herrmann/pdf_binder
Author: Peter Herrmann
Author-email: herrmannp7@gmail.com
License: MIT
Platform: UNKNOWN
License-File: LICENSE
Requires-Dist: Pillow
Requires-Dist: PyPDF2
Requires-Dist: pdf2image
Requires-Dist: tqdm
